nlp_datasets/__init__.py
nlp_datasets/dssm/__init__.py
nlp_datasets/dssm/dssm_dataset.py
nlp_datasets/dssm/dssm_dataset_test.py
nlp_datasets/dssm/ns_generator.py
nlp_datasets/dssm/ns_generator_test.py
nlp_datasets/dssm/query_doc_datasets.py
nlp_datasets/dssm/query_doc_datasets_test.py
nlp_datasets/matchpyramid/__init__.py
nlp_datasets/matchpyramid/match_pyramid_dataset.py
nlp_datasets/matchpyramid/match_pyramid_dataset_test.py
nlp_datasets/nlp/__init__.py
nlp_datasets/nlp/xy_dataset.py
nlp_datasets/nlp/xy_dataset_test.py
nlp_datasets/nlp/xyz_dataset.py
nlp_datasets/nlp/xyz_dataset_test.py
nlp_datasets/nmt/__init__.py
nlp_datasets/nmt/legacy_datasets.py
nlp_datasets/nmt/legacy_datasets_test.py
nlp_datasets/nmt/nmt_dataset.py
nlp_datasets/nmt/nmt_dataset_test.py
nlp_datasets/nmt/src_tgt_datasets.py
nlp_datasets/nmt/src_tgt_datasets_test.py
nlp_datasets/seq2seq/__init__.py
nlp_datasets/seq2seq/seq2seq_dataset.py
nlp_datasets/seq2seq/seq2seq_dataset_test.py
nlp_datasets/utils/__init__.py
nlp_datasets/utils/data_dir_utils.py
naivenmt_datasets-0.0.7.dist-info/LICENSE
naivenmt_datasets-0.0.7.dist-info/METADATA
naivenmt_datasets-0.0.7.dist-info/WHEEL
naivenmt_datasets-0.0.7.dist-info/top_level.txt
naivenmt_datasets-0.0.7.dist-info/RECORD
