Metadata-Version: 2.1
Name: naivenmt-datasets
Version: 0.0.7
Summary: A dataset utils repository. For tensorflow 2.x only!
Home-page: https://github.com/naivenmt/datasets
Author: ZhouYang Luo
Author-email: zhouyang.luo@gmail.com
License: MIT License
Platform: UNKNOWN
Classifier: Programming Language :: Python :: 3.6
Classifier: License :: OSI Approved :: MIT License
Classifier: Operating System :: OS Independent
Requires-Dist: deprecated (>=1.2.5)
